fennel_dataset/__init__.py
fennel_dataset/lib.py
fennel_dataset-0.1.0.dist-info/WHEEL
fennel_dataset-0.1.0.dist-info/METADATA
fennel_dataset-0.1.0.dist-info/RECORD
