Metadata-Version: 2.1
Name: fennel-dataset
Version: 0.1.0
Summary: Empty library from fennel_dataset for Github Actions
Author: Aditya Nambiar
Author-email: adityanambiar@fennel.ai
Requires-Python: >=3.7,<4.0
Classifier: Programming Language :: Python :: 3
Classifier: Programming Language :: Python :: 3.10
Classifier: Programming Language :: Python :: 3.7
Classifier: Programming Language :: Python :: 3.8
Classifier: Programming Language :: Python :: 3.9
